<?xml version="1.0" encoding="UTF-8"?><kodeliste xmlns="urn:no:skatteetaten:kodelistebibliotek:domain:v1">
  <tekniskNavn>2023_konsumprisindeksVannkraft</tekniskNavn>
  <beskrivelse>
    <spraakTekst>
      <tekst>Kodeliste over konsumpriser som benyttes til beregning av konsumprisindeksjusterte investeringskostnader for anleggsmidler innen vannkraft.</tekst>
      <spraak>no</spraak>
    </spraakTekst>
  </beskrivelse>
  <kode>
    <tekniskNavn>2019</tekniskNavn>
    <beskrivelse>
      <spraakTekst>
        <tekst>2019</tekst>
        <spraak>no</spraak>
      </spraakTekst>
    </beskrivelse>
    <visningsnavn>
      <spraakTekst>
        <tekst>2019</tekst>
        <spraak>nb_NO</spraak>
      </spraakTekst>
      <spraakTekst>
        <tekst>2019</tekst>
        <spraak>nn_NO</spraak>
      </spraakTekst>
      <spraakTekst>
        <tekst>2019</tekst>
        <spraak>se_NO</spraak>
      </spraakTekst>
      <spraakTekst>
        <tekst>2019</tekst>
        <spraak>en_US</spraak>
      </spraakTekst>
    </visningsnavn>
    <kodetillegg>
      <konsumprisindeks>110.8</konsumprisindeks>
    </kodetillegg>
  </kode>
  <kode>
    <tekniskNavn>2020</tekniskNavn>
    <beskrivelse>
      <spraakTekst>
        <tekst>2020</tekst>
        <spraak>no</spraak>
      </spraakTekst>
    </beskrivelse>
    <visningsnavn>
      <spraakTekst>
        <tekst>2020</tekst>
        <spraak>nb_NO</spraak>
      </spraakTekst>
      <spraakTekst>
        <tekst>2020</tekst>
        <spraak>nn_NO</spraak>
      </spraakTekst>
      <spraakTekst>
        <tekst>2020</tekst>
        <spraak>se_NO</spraak>
      </spraakTekst>
      <spraakTekst>
        <tekst>2020</tekst>
        <spraak>en_US</spraak>
      </spraakTekst>
    </visningsnavn>
    <kodetillegg>
      <konsumprisindeks>112.2</konsumprisindeks>
    </kodetillegg>
  </kode>
  <kode>
    <tekniskNavn>2021</tekniskNavn>
    <beskrivelse>
      <spraakTekst>
        <tekst>2021</tekst>
        <spraak>no</spraak>
      </spraakTekst>
    </beskrivelse>
    <visningsnavn>
      <spraakTekst>
        <tekst>2021</tekst>
        <spraak>nb_NO</spraak>
      </spraakTekst>
      <spraakTekst>
        <tekst>2021</tekst>
        <spraak>nn_NO</spraak>
      </spraakTekst>
      <spraakTekst>
        <tekst>2021</tekst>
        <spraak>se_NO</spraak>
      </spraakTekst>
      <spraakTekst>
        <tekst>2021</tekst>
        <spraak>en_US</spraak>
      </spraakTekst>
    </visningsnavn>
    <kodetillegg>
      <konsumprisindeks>116.1</konsumprisindeks>
    </kodetillegg>
  </kode>
  <kode>
    <tekniskNavn>2022</tekniskNavn>
    <beskrivelse>
      <spraakTekst>
        <tekst>2022</tekst>
        <spraak>no</spraak>
      </spraakTekst>
    </beskrivelse>
    <visningsnavn>
      <spraakTekst>
        <tekst>2022</tekst>
        <spraak>nb_NO</spraak>
      </spraakTekst>
      <spraakTekst>
        <tekst>2022</tekst>
        <spraak>nn_NO</spraak>
      </spraakTekst>
      <spraakTekst>
        <tekst>2022</tekst>
        <spraak>se_NO</spraak>
      </spraakTekst>
      <spraakTekst>
        <tekst>2022</tekst>
        <spraak>en_US</spraak>
      </spraakTekst>
    </visningsnavn>
    <kodetillegg>
      <konsumprisindeks>122.8</konsumprisindeks>
    </kodetillegg>
  </kode>
  <kode>
    <tekniskNavn>2023</tekniskNavn>
    <beskrivelse>
      <spraakTekst>
        <tekst>2023</tekst>
        <spraak>no</spraak>
      </spraakTekst>
    </beskrivelse>
    <visningsnavn>
      <spraakTekst>
        <tekst>2023</tekst>
        <spraak>nb_NO</spraak>
      </spraakTekst>
      <spraakTekst>
        <tekst>2023</tekst>
        <spraak>nn_NO</spraak>
      </spraakTekst>
      <spraakTekst>
        <tekst>2023</tekst>
        <spraak>se_NO</spraak>
      </spraakTekst>
      <spraakTekst>
        <tekst>2023</tekst>
        <spraak>en_US</spraak>
      </spraakTekst>
    </visningsnavn>
    <kodetillegg>
      <konsumprisindeks>125.0</konsumprisindeks>
    </kodetillegg>
  </kode>
  <lokaltForvaltet>true</lokaltForvaltet>
</kodeliste>
