<?xml version='1.0' encoding='UTF-8'?>
<skattemelding xmlns="urn:no:skatteetaten:fastsetting:formueinntekt:skattemelding:upersonlig:ekstern:v2">
    <partsnummer>{partsnummer}</partsnummer>
    <inntektsaar>2022</inntektsaar>
    <inntektOgUnderskudd>
        <inntekt>
            <samletMottattKonsernbidrag>
                <beloepSomHeltall>300</beloepSomHeltall>
            </samletMottattKonsernbidrag>
            <mottattKonsernbidrag>
                <id>1</id>
                <avgiversOrganisasjonsnummer>
                    <organisasjonsnummer>310817074</organisasjonsnummer>
                </avgiversOrganisasjonsnummer>
                <konsernbidrag>
                    <beloepMedSkattemessigVirkning>
                        <beloepSomHeltall>300</beloepSomHeltall>
                    </beloepMedSkattemessigVirkning>
                </konsernbidrag>
                <avgiversKonserntilknytning>
                    <konserntilknytningstype>
                        <konserntilknytningstype>annen</konserntilknytningstype>
                    </konserntilknytningstype>
                    <stemmerettsbegrensningForeligger>
                        <boolsk>false</boolsk>
                    </stemmerettsbegrensningForeligger>
                </avgiversKonserntilknytning>
            </mottattKonsernbidrag>
        </inntekt>
        <inntektsfradrag>
            <underskudd>
                <beloepSomHeltall>1057000</beloepSomHeltall>
            </underskudd>
            <samletAvgittKonsernbidrag>
                <beloepSomHeltall>100</beloepSomHeltall>
            </samletAvgittKonsernbidrag>
            <avgittKonsernbidrag>
                <id>1</id>
                <mottakersOrganisasjonsnummer>
                    <organisasjonsnummer>310817074</organisasjonsnummer>
                </mottakersOrganisasjonsnummer>
                <konsernbidrag>
                    <beloepMedSkattemessigVirkning>
                        <beloepSomHeltall>100</beloepSomHeltall>
                    </beloepMedSkattemessigVirkning>
                </konsernbidrag>
                <mottakersKonserntilknytning>
                    <konserntilknytningstype>
                        <konserntilknytningstype>annen</konserntilknytningstype>
                    </konserntilknytningstype>
                    <stemmerettsbegrensningForeligger>
                        <boolsk>false</boolsk>
                    </stemmerettsbegrensningForeligger>
                </mottakersKonserntilknytning>
            </avgittKonsernbidrag>
        </inntektsfradrag>
        <underskuddTilFremfoering>
            <fremfoerbartUnderskuddIInntekt>
                <beloep>
                    <beloepSomHeltall>1056800</beloepSomHeltall>
                </beloep>
            </fremfoerbartUnderskuddIInntekt>
        </underskuddTilFremfoering>
        <samletUnderskudd>
            <beloep>
                <beloepSomHeltall>1056800</beloepSomHeltall>
            </beloep>
        </samletUnderskudd>
        <konsernbidragSkalBekreftesAvRevisor>true</konsernbidragSkalBekreftesAvRevisor>
    </inntektOgUnderskudd>
</skattemelding>