<?xml version="1.0" encoding="UTF-8"?><kodeliste xmlns="urn:no:skatteetaten:kodelistebibliotek:domain:v1">
  <tekniskNavn>2024_konsumprisindeksVannkraft</tekniskNavn>
  <beskrivelse>
    <spraakTekst>
      <tekst>Kodeliste over konsumpriser som benyttes til beregning av konsumprisindeksjusterte investeringskostnader for anleggsmidler innen vannkraft.</tekst>
      <spraak>no</spraak>
    </spraakTekst>
  </beskrivelse>
  <kode>
    <tekniskNavn>1997</tekniskNavn>
    <beskrivelse>
      <spraakTekst>
        <tekst>1997</tekst>
        <spraak>no</spraak>
      </spraakTekst>
    </beskrivelse>
    <visningsnavn>
      <spraakTekst>
        <tekst>1997</tekst>
        <spraak>nb_NO</spraak>
      </spraakTekst>
      <spraakTekst>
        <tekst>1997</tekst>
        <spraak>nn_NO</spraak>
      </spraakTekst>
      <spraakTekst>
        <tekst>1997</tekst>
        <spraak>se_NO</spraak>
      </spraakTekst>
      <spraakTekst>
        <tekst>1997</tekst>
        <spraak>en_US</spraak>
      </spraakTekst>
    </visningsnavn>
    <kodetillegg>
      <konsumprisindeks>69.9</konsumprisindeks>
    </kodetillegg>
  </kode>
  <kode>
    <tekniskNavn>1998</tekniskNavn>
    <beskrivelse>
      <spraakTekst>
        <tekst>1998</tekst>
        <spraak>no</spraak>
      </spraakTekst>
    </beskrivelse>
    <visningsnavn>
      <spraakTekst>
        <tekst>1998</tekst>
        <spraak>nb_NO</spraak>
      </spraakTekst>
      <spraakTekst>
        <tekst>1998</tekst>
        <spraak>nn_NO</spraak>
      </spraakTekst>
      <spraakTekst>
        <tekst>1998</tekst>
        <spraak>se_NO</spraak>
      </spraakTekst>
      <spraakTekst>
        <tekst>1998</tekst>
        <spraak>en_US</spraak>
      </spraakTekst>
    </visningsnavn>
    <kodetillegg>
      <konsumprisindeks>71.5</konsumprisindeks>
    </kodetillegg>
  </kode>
  <kode>
    <tekniskNavn>1999</tekniskNavn>
    <beskrivelse>
      <spraakTekst>
        <tekst>1999</tekst>
        <spraak>no</spraak>
      </spraakTekst>
    </beskrivelse>
    <visningsnavn>
      <spraakTekst>
        <tekst>1999</tekst>
        <spraak>nb_NO</spraak>
      </spraakTekst>
      <spraakTekst>
        <tekst>1999</tekst>
        <spraak>nn_NO</spraak>
      </spraakTekst>
      <spraakTekst>
        <tekst>1999</tekst>
        <spraak>se_NO</spraak>
      </spraakTekst>
      <spraakTekst>
        <tekst>1999</tekst>
        <spraak>en_US</spraak>
      </spraakTekst>
    </visningsnavn>
    <kodetillegg>
      <konsumprisindeks>73.2</konsumprisindeks>
    </kodetillegg>
  </kode>
  <kode>
    <tekniskNavn>2000</tekniskNavn>
    <beskrivelse>
      <spraakTekst>
        <tekst>2000</tekst>
        <spraak>no</spraak>
      </spraakTekst>
    </beskrivelse>
    <visningsnavn>
      <spraakTekst>
        <tekst>2000</tekst>
        <spraak>nb_NO</spraak>
      </spraakTekst>
      <spraakTekst>
        <tekst>2000</tekst>
        <spraak>nn_NO</spraak>
      </spraakTekst>
      <spraakTekst>
        <tekst>2000</tekst>
        <spraak>se_NO</spraak>
      </spraakTekst>
      <spraakTekst>
        <tekst>2000</tekst>
        <spraak>en_US</spraak>
      </spraakTekst>
    </visningsnavn>
    <kodetillegg>
      <konsumprisindeks>75.5</konsumprisindeks>
    </kodetillegg>
  </kode>
  <kode>
    <tekniskNavn>2001</tekniskNavn>
    <beskrivelse>
      <spraakTekst>
        <tekst>2001</tekst>
        <spraak>no</spraak>
      </spraakTekst>
    </beskrivelse>
    <visningsnavn>
      <spraakTekst>
        <tekst>2001</tekst>
        <spraak>nb_NO</spraak>
      </spraakTekst>
      <spraakTekst>
        <tekst>2001</tekst>
        <spraak>nn_NO</spraak>
      </spraakTekst>
      <spraakTekst>
        <tekst>2001</tekst>
        <spraak>se_NO</spraak>
      </spraakTekst>
      <spraakTekst>
        <tekst>2001</tekst>
        <spraak>en_US</spraak>
      </spraakTekst>
    </visningsnavn>
    <kodetillegg>
      <konsumprisindeks>77.7</konsumprisindeks>
    </kodetillegg>
  </kode>
  <kode>
    <tekniskNavn>2002</tekniskNavn>
    <beskrivelse>
      <spraakTekst>
        <tekst>2002</tekst>
        <spraak>no</spraak>
      </spraakTekst>
    </beskrivelse>
    <visningsnavn>
      <spraakTekst>
        <tekst>2002</tekst>
        <spraak>nb_NO</spraak>
      </spraakTekst>
      <spraakTekst>
        <tekst>2002</tekst>
        <spraak>nn_NO</spraak>
      </spraakTekst>
      <spraakTekst>
        <tekst>2002</tekst>
        <spraak>se_NO</spraak>
      </spraakTekst>
      <spraakTekst>
        <tekst>2002</tekst>
        <spraak>en_US</spraak>
      </spraakTekst>
    </visningsnavn>
    <kodetillegg>
      <konsumprisindeks>78.7</konsumprisindeks>
    </kodetillegg>
  </kode>
  <kode>
    <tekniskNavn>2003</tekniskNavn>
    <beskrivelse>
      <spraakTekst>
        <tekst>2003</tekst>
        <spraak>no</spraak>
      </spraakTekst>
    </beskrivelse>
    <visningsnavn>
      <spraakTekst>
        <tekst>2003</tekst>
        <spraak>nb_NO</spraak>
      </spraakTekst>
      <spraakTekst>
        <tekst>2003</tekst>
        <spraak>nn_NO</spraak>
      </spraakTekst>
      <spraakTekst>
        <tekst>2003</tekst>
        <spraak>se_NO</spraak>
      </spraakTekst>
      <spraakTekst>
        <tekst>2003</tekst>
        <spraak>en_US</spraak>
      </spraakTekst>
    </visningsnavn>
    <kodetillegg>
      <konsumprisindeks>80.7</konsumprisindeks>
    </kodetillegg>
  </kode>
  <kode>
    <tekniskNavn>2004</tekniskNavn>
    <beskrivelse>
      <spraakTekst>
        <tekst>2004</tekst>
        <spraak>no</spraak>
      </spraakTekst>
    </beskrivelse>
    <visningsnavn>
      <spraakTekst>
        <tekst>2004</tekst>
        <spraak>nb_NO</spraak>
      </spraakTekst>
      <spraakTekst>
        <tekst>2004</tekst>
        <spraak>nn_NO</spraak>
      </spraakTekst>
      <spraakTekst>
        <tekst>2004</tekst>
        <spraak>se_NO</spraak>
      </spraakTekst>
      <spraakTekst>
        <tekst>2004</tekst>
        <spraak>en_US</spraak>
      </spraakTekst>
    </visningsnavn>
    <kodetillegg>
      <konsumprisindeks>81.0</konsumprisindeks>
    </kodetillegg>
  </kode>
  <kode>
    <tekniskNavn>2005</tekniskNavn>
    <beskrivelse>
      <spraakTekst>
        <tekst>2005</tekst>
        <spraak>no</spraak>
      </spraakTekst>
    </beskrivelse>
    <visningsnavn>
      <spraakTekst>
        <tekst>2005</tekst>
        <spraak>nb_NO</spraak>
      </spraakTekst>
      <spraakTekst>
        <tekst>2005</tekst>
        <spraak>nn_NO</spraak>
      </spraakTekst>
      <spraakTekst>
        <tekst>2005</tekst>
        <spraak>se_NO</spraak>
      </spraakTekst>
      <spraakTekst>
        <tekst>2005</tekst>
        <spraak>en_US</spraak>
      </spraakTekst>
    </visningsnavn>
    <kodetillegg>
      <konsumprisindeks>82.3</konsumprisindeks>
    </kodetillegg>
  </kode>
  <kode>
    <tekniskNavn>2006</tekniskNavn>
    <beskrivelse>
      <spraakTekst>
        <tekst>2006</tekst>
        <spraak>no</spraak>
      </spraakTekst>
    </beskrivelse>
    <visningsnavn>
      <spraakTekst>
        <tekst>2006</tekst>
        <spraak>nb_NO</spraak>
      </spraakTekst>
      <spraakTekst>
        <tekst>2006</tekst>
        <spraak>nn_NO</spraak>
      </spraakTekst>
      <spraakTekst>
        <tekst>2006</tekst>
        <spraak>se_NO</spraak>
      </spraakTekst>
      <spraakTekst>
        <tekst>2006</tekst>
        <spraak>en_US</spraak>
      </spraakTekst>
    </visningsnavn>
    <kodetillegg>
      <konsumprisindeks>84.2</konsumprisindeks>
    </kodetillegg>
  </kode>
  <kode>
    <tekniskNavn>2007</tekniskNavn>
    <beskrivelse>
      <spraakTekst>
        <tekst>2007</tekst>
        <spraak>no</spraak>
      </spraakTekst>
    </beskrivelse>
    <visningsnavn>
      <spraakTekst>
        <tekst>2007</tekst>
        <spraak>nb_NO</spraak>
      </spraakTekst>
      <spraakTekst>
        <tekst>2007</tekst>
        <spraak>nn_NO</spraak>
      </spraakTekst>
      <spraakTekst>
        <tekst>2007</tekst>
        <spraak>se_NO</spraak>
      </spraakTekst>
      <spraakTekst>
        <tekst>2007</tekst>
        <spraak>en_US</spraak>
      </spraakTekst>
    </visningsnavn>
    <kodetillegg>
      <konsumprisindeks>84.8</konsumprisindeks>
    </kodetillegg>
  </kode>
  <kode>
    <tekniskNavn>2008</tekniskNavn>
    <beskrivelse>
      <spraakTekst>
        <tekst>2008</tekst>
        <spraak>no</spraak>
      </spraakTekst>
    </beskrivelse>
    <visningsnavn>
      <spraakTekst>
        <tekst>2008</tekst>
        <spraak>nb_NO</spraak>
      </spraakTekst>
      <spraakTekst>
        <tekst>2008</tekst>
        <spraak>nn_NO</spraak>
      </spraakTekst>
      <spraakTekst>
        <tekst>2008</tekst>
        <spraak>se_NO</spraak>
      </spraakTekst>
      <spraakTekst>
        <tekst>2008</tekst>
        <spraak>en_US</spraak>
      </spraakTekst>
    </visningsnavn>
    <kodetillegg>
      <konsumprisindeks>88.0</konsumprisindeks>
    </kodetillegg>
  </kode>
  <kode>
    <tekniskNavn>2009</tekniskNavn>
    <beskrivelse>
      <spraakTekst>
        <tekst>2009</tekst>
        <spraak>no</spraak>
      </spraakTekst>
    </beskrivelse>
    <visningsnavn>
      <spraakTekst>
        <tekst>2009</tekst>
        <spraak>nb_NO</spraak>
      </spraakTekst>
      <spraakTekst>
        <tekst>2009</tekst>
        <spraak>nn_NO</spraak>
      </spraakTekst>
      <spraakTekst>
        <tekst>2009</tekst>
        <spraak>se_NO</spraak>
      </spraakTekst>
      <spraakTekst>
        <tekst>2009</tekst>
        <spraak>en_US</spraak>
      </spraakTekst>
    </visningsnavn>
    <kodetillegg>
      <konsumprisindeks>89.9</konsumprisindeks>
    </kodetillegg>
  </kode>
  <kode>
    <tekniskNavn>2010</tekniskNavn>
    <beskrivelse>
      <spraakTekst>
        <tekst>2010</tekst>
        <spraak>no</spraak>
      </spraakTekst>
    </beskrivelse>
    <visningsnavn>
      <spraakTekst>
        <tekst>2010</tekst>
        <spraak>nb_NO</spraak>
      </spraakTekst>
      <spraakTekst>
        <tekst>2010</tekst>
        <spraak>nn_NO</spraak>
      </spraakTekst>
      <spraakTekst>
        <tekst>2010</tekst>
        <spraak>se_NO</spraak>
      </spraakTekst>
      <spraakTekst>
        <tekst>2010</tekst>
        <spraak>en_US</spraak>
      </spraakTekst>
    </visningsnavn>
    <kodetillegg>
      <konsumprisindeks>92.1</konsumprisindeks>
    </kodetillegg>
  </kode>
  <kode>
    <tekniskNavn>2011</tekniskNavn>
    <beskrivelse>
      <spraakTekst>
        <tekst>2011</tekst>
        <spraak>no</spraak>
      </spraakTekst>
    </beskrivelse>
    <visningsnavn>
      <spraakTekst>
        <tekst>2011</tekst>
        <spraak>nb_NO</spraak>
      </spraakTekst>
      <spraakTekst>
        <tekst>2011</tekst>
        <spraak>nn_NO</spraak>
      </spraakTekst>
      <spraakTekst>
        <tekst>2011</tekst>
        <spraak>se_NO</spraak>
      </spraakTekst>
      <spraakTekst>
        <tekst>2011</tekst>
        <spraak>en_US</spraak>
      </spraakTekst>
    </visningsnavn>
    <kodetillegg>
      <konsumprisindeks>93.3</konsumprisindeks>
    </kodetillegg>
  </kode>
  <kode>
    <tekniskNavn>2012</tekniskNavn>
    <beskrivelse>
      <spraakTekst>
        <tekst>2012</tekst>
        <spraak>no</spraak>
      </spraakTekst>
    </beskrivelse>
    <visningsnavn>
      <spraakTekst>
        <tekst>2012</tekst>
        <spraak>nb_NO</spraak>
      </spraakTekst>
      <spraakTekst>
        <tekst>2012</tekst>
        <spraak>nn_NO</spraak>
      </spraakTekst>
      <spraakTekst>
        <tekst>2012</tekst>
        <spraak>se_NO</spraak>
      </spraakTekst>
      <spraakTekst>
        <tekst>2012</tekst>
        <spraak>en_US</spraak>
      </spraakTekst>
    </visningsnavn>
    <kodetillegg>
      <konsumprisindeks>93.9</konsumprisindeks>
    </kodetillegg>
  </kode>
  <kode>
    <tekniskNavn>2013</tekniskNavn>
    <beskrivelse>
      <spraakTekst>
        <tekst>2013</tekst>
        <spraak>no</spraak>
      </spraakTekst>
    </beskrivelse>
    <visningsnavn>
      <spraakTekst>
        <tekst>2013</tekst>
        <spraak>nb_NO</spraak>
      </spraakTekst>
      <spraakTekst>
        <tekst>2013</tekst>
        <spraak>nn_NO</spraak>
      </spraakTekst>
      <spraakTekst>
        <tekst>2013</tekst>
        <spraak>se_NO</spraak>
      </spraakTekst>
      <spraakTekst>
        <tekst>2013</tekst>
        <spraak>en_US</spraak>
      </spraakTekst>
    </visningsnavn>
    <kodetillegg>
      <konsumprisindeks>95.9</konsumprisindeks>
    </kodetillegg>
  </kode>
  <kode>
    <tekniskNavn>2014</tekniskNavn>
    <beskrivelse>
      <spraakTekst>
        <tekst>2014</tekst>
        <spraak>no</spraak>
      </spraakTekst>
    </beskrivelse>
    <visningsnavn>
      <spraakTekst>
        <tekst>2014</tekst>
        <spraak>nb_NO</spraak>
      </spraakTekst>
      <spraakTekst>
        <tekst>2014</tekst>
        <spraak>nn_NO</spraak>
      </spraakTekst>
      <spraakTekst>
        <tekst>2014</tekst>
        <spraak>se_NO</spraak>
      </spraakTekst>
      <spraakTekst>
        <tekst>2014</tekst>
        <spraak>en_US</spraak>
      </spraakTekst>
    </visningsnavn>
    <kodetillegg>
      <konsumprisindeks>97.9</konsumprisindeks>
    </kodetillegg>
  </kode>
  <kode>
    <tekniskNavn>2015</tekniskNavn>
    <beskrivelse>
      <spraakTekst>
        <tekst>2015</tekst>
        <spraak>no</spraak>
      </spraakTekst>
    </beskrivelse>
    <visningsnavn>
      <spraakTekst>
        <tekst>2015</tekst>
        <spraak>nb_NO</spraak>
      </spraakTekst>
      <spraakTekst>
        <tekst>2015</tekst>
        <spraak>nn_NO</spraak>
      </spraakTekst>
      <spraakTekst>
        <tekst>2015</tekst>
        <spraak>se_NO</spraak>
      </spraakTekst>
      <spraakTekst>
        <tekst>2015</tekst>
        <spraak>en_US</spraak>
      </spraakTekst>
    </visningsnavn>
    <kodetillegg>
      <konsumprisindeks>100.0</konsumprisindeks>
    </kodetillegg>
  </kode>
  <kode>
    <tekniskNavn>2016</tekniskNavn>
    <beskrivelse>
      <spraakTekst>
        <tekst>2016</tekst>
        <spraak>no</spraak>
      </spraakTekst>
    </beskrivelse>
    <visningsnavn>
      <spraakTekst>
        <tekst>2016</tekst>
        <spraak>nb_NO</spraak>
      </spraakTekst>
      <spraakTekst>
        <tekst>2016</tekst>
        <spraak>nn_NO</spraak>
      </spraakTekst>
      <spraakTekst>
        <tekst>2016</tekst>
        <spraak>se_NO</spraak>
      </spraakTekst>
      <spraakTekst>
        <tekst>2016</tekst>
        <spraak>en_US</spraak>
      </spraakTekst>
    </visningsnavn>
    <kodetillegg>
      <konsumprisindeks>103.6</konsumprisindeks>
    </kodetillegg>
  </kode>
  <kode>
    <tekniskNavn>2017</tekniskNavn>
    <beskrivelse>
      <spraakTekst>
        <tekst>2017</tekst>
        <spraak>no</spraak>
      </spraakTekst>
    </beskrivelse>
    <visningsnavn>
      <spraakTekst>
        <tekst>2017</tekst>
        <spraak>nb_NO</spraak>
      </spraakTekst>
      <spraakTekst>
        <tekst>2017</tekst>
        <spraak>nn_NO</spraak>
      </spraakTekst>
      <spraakTekst>
        <tekst>2017</tekst>
        <spraak>se_NO</spraak>
      </spraakTekst>
      <spraakTekst>
        <tekst>2017</tekst>
        <spraak>en_US</spraak>
      </spraakTekst>
    </visningsnavn>
    <kodetillegg>
      <konsumprisindeks>105.5</konsumprisindeks>
    </kodetillegg>
  </kode>
  <kode>
    <tekniskNavn>2018</tekniskNavn>
    <beskrivelse>
      <spraakTekst>
        <tekst>2018</tekst>
        <spraak>no</spraak>
      </spraakTekst>
    </beskrivelse>
    <visningsnavn>
      <spraakTekst>
        <tekst>2018</tekst>
        <spraak>nb_NO</spraak>
      </spraakTekst>
      <spraakTekst>
        <tekst>2018</tekst>
        <spraak>nn_NO</spraak>
      </spraakTekst>
      <spraakTekst>
        <tekst>2018</tekst>
        <spraak>se_NO</spraak>
      </spraakTekst>
      <spraakTekst>
        <tekst>2018</tekst>
        <spraak>en_US</spraak>
      </spraakTekst>
    </visningsnavn>
    <kodetillegg>
      <konsumprisindeks>108.4</konsumprisindeks>
    </kodetillegg>
  </kode>
  <kode>
    <tekniskNavn>2019</tekniskNavn>
    <beskrivelse>
      <spraakTekst>
        <tekst>2019</tekst>
        <spraak>no</spraak>
      </spraakTekst>
    </beskrivelse>
    <visningsnavn>
      <spraakTekst>
        <tekst>2019</tekst>
        <spraak>nb_NO</spraak>
      </spraakTekst>
      <spraakTekst>
        <tekst>2019</tekst>
        <spraak>nn_NO</spraak>
      </spraakTekst>
      <spraakTekst>
        <tekst>2019</tekst>
        <spraak>se_NO</spraak>
      </spraakTekst>
      <spraakTekst>
        <tekst>2019</tekst>
        <spraak>en_US</spraak>
      </spraakTekst>
    </visningsnavn>
    <kodetillegg>
      <konsumprisindeks>110.8</konsumprisindeks>
    </kodetillegg>
  </kode>
  <kode>
    <tekniskNavn>2020</tekniskNavn>
    <beskrivelse>
      <spraakTekst>
        <tekst>2020</tekst>
        <spraak>no</spraak>
      </spraakTekst>
    </beskrivelse>
    <visningsnavn>
      <spraakTekst>
        <tekst>2020</tekst>
        <spraak>nb_NO</spraak>
      </spraakTekst>
      <spraakTekst>
        <tekst>2020</tekst>
        <spraak>nn_NO</spraak>
      </spraakTekst>
      <spraakTekst>
        <tekst>2020</tekst>
        <spraak>se_NO</spraak>
      </spraakTekst>
      <spraakTekst>
        <tekst>2020</tekst>
        <spraak>en_US</spraak>
      </spraakTekst>
    </visningsnavn>
    <kodetillegg>
      <konsumprisindeks>112.2</konsumprisindeks>
    </kodetillegg>
  </kode>
  <kode>
    <tekniskNavn>2021</tekniskNavn>
    <beskrivelse>
      <spraakTekst>
        <tekst>2021</tekst>
        <spraak>no</spraak>
      </spraakTekst>
    </beskrivelse>
    <visningsnavn>
      <spraakTekst>
        <tekst>2021</tekst>
        <spraak>nb_NO</spraak>
      </spraakTekst>
      <spraakTekst>
        <tekst>2021</tekst>
        <spraak>nn_NO</spraak>
      </spraakTekst>
      <spraakTekst>
        <tekst>2021</tekst>
        <spraak>se_NO</spraak>
      </spraakTekst>
      <spraakTekst>
        <tekst>2021</tekst>
        <spraak>en_US</spraak>
      </spraakTekst>
    </visningsnavn>
    <kodetillegg>
      <konsumprisindeks>116.1</konsumprisindeks>
    </kodetillegg>
  </kode>
  <kode>
    <tekniskNavn>2022</tekniskNavn>
    <beskrivelse>
      <spraakTekst>
        <tekst>2022</tekst>
        <spraak>no</spraak>
      </spraakTekst>
    </beskrivelse>
    <visningsnavn>
      <spraakTekst>
        <tekst>2022</tekst>
        <spraak>nb_NO</spraak>
      </spraakTekst>
      <spraakTekst>
        <tekst>2022</tekst>
        <spraak>nn_NO</spraak>
      </spraakTekst>
      <spraakTekst>
        <tekst>2022</tekst>
        <spraak>se_NO</spraak>
      </spraakTekst>
      <spraakTekst>
        <tekst>2022</tekst>
        <spraak>en_US</spraak>
      </spraakTekst>
    </visningsnavn>
    <kodetillegg>
      <konsumprisindeks>122.8</konsumprisindeks>
    </kodetillegg>
  </kode>
  <kode>
    <tekniskNavn>2023</tekniskNavn>
    <beskrivelse>
      <spraakTekst>
        <tekst>2023</tekst>
        <spraak>no</spraak>
      </spraakTekst>
    </beskrivelse>
    <visningsnavn>
      <spraakTekst>
        <tekst>2023</tekst>
        <spraak>nb_NO</spraak>
      </spraakTekst>
      <spraakTekst>
        <tekst>2023</tekst>
        <spraak>nn_NO</spraak>
      </spraakTekst>
      <spraakTekst>
        <tekst>2023</tekst>
        <spraak>se_NO</spraak>
      </spraakTekst>
      <spraakTekst>
        <tekst>2023</tekst>
        <spraak>en_US</spraak>
      </spraakTekst>
    </visningsnavn>
    <kodetillegg>
      <konsumprisindeks>129.6</konsumprisindeks>
    </kodetillegg>
  </kode>
  <lokaltForvaltet>true</lokaltForvaltet>
</kodeliste>
